{
  "Avg": {
    "gpufbmem": 0.0,
    "gpumempct": 0.0,
    "gpusmpct": 0.0,
    "ngpus": 0.0,
    "nprocs": 2.0,
    "nthreads": 8.0,
    "pss": 3074295.0,
    "rchar": 1303674677.0,
    "read_bytes": 0.0,
    "rss": 3237492.0,
    "rx_bytes": 1542490.0,
    "rx_packets": 3569.0,
    "swap": 0.0,
    "tx_bytes": 1086001.0,
    "tx_packets": 4414.0,
    "vmem": 3933792.0,
    "wchar": 72997501.0,
    "write_bytes": 71855542.0
  },
  "HW": {
    "cpu": {
      "CPUs": 48,
      "CoresPerSocket": 24,
      "ModelName": "AMD EPYC 7413 24-Core Processor",
      "Sockets": 1,
      "ThreadsPerCore": 2
    },
    "gpu": {
      "gpu_0": {
        "name": "NVIDIA RTX A5000",
        "sm_freq": 2100,
        "total_mem": 25153536
      },
      "nGPU": 1
    },
    "mem": {
      "MemTotal": 131219192
    }
  },
  "Max": {
    "gpufbmem": 0,
    "gpumempct": 0,
    "gpusmpct": 0,
    "ngpus": 0,
    "nprocs": 2,
    "nthreads": 11,
    "pss": 4643210,
    "rchar": 821315047,
    "read_bytes": 0,
    "rss": 4876016,
    "rx_bytes": 971769,
    "rx_packets": 2249,
    "stime": 3,
    "swap": 0,
    "tx_bytes": 684181,
    "tx_packets": 2781,
    "utime": 343,
    "vmem": 5648948,
    "wchar": 45988426,
    "write_bytes": 45268992,
    "wtime": 63
  },
  "prmon": {
    "Version": "3.1.1"
  }
}
