{
  "Avg": {
    "gpufbmem": 0.0,
    "gpumempct": 0.0,
    "gpusmpct": 0.0,
    "ngpus": 0.0,
    "nprocs": 2.0,
    "nthreads": 10.5,
    "pss": 3601292.0,
    "rchar": 2060144446.0,
    "read_bytes": 0.0,
    "rss": 3729672.0,
    "rx_bytes": 2992768.0,
    "rx_packets": 6775.0,
    "swap": 0.0,
    "tx_bytes": 2058512.0,
    "tx_packets": 8284.0,
    "vmem": 4416846.0,
    "wchar": 44551450.0,
    "write_bytes": 41523200.0
  },
  "HW": {
    "cpu": {
      "CPUs": 48,
      "CoresPerSocket": 24,
      "ModelName": "AMD EPYC 7413 24-Core Processor",
      "Sockets": 1,
      "ThreadsPerCore": 2
    },
    "gpu": {
      "gpu_0": {
        "name": "NVIDIA RTX A5000",
        "sm_freq": 2100,
        "total_mem": 25153536
      },
      "nGPU": 1
    },
    "mem": {
      "MemTotal": 131219192
    }
  },
  "Max": {
    "gpufbmem": 0,
    "gpumempct": 0,
    "gpusmpct": 0,
    "ngpus": 0,
    "nprocs": 2,
    "nthreads": 19,
    "pss": 7149634,
    "rchar": 659246223,
    "read_bytes": 0,
    "rss": 7382484,
    "rx_bytes": 957686,
    "rx_packets": 2168,
    "stime": 3,
    "swap": 0,
    "tx_bytes": 658724,
    "tx_packets": 2651,
    "utime": 160,
    "vmem": 8220568,
    "wchar": 14256464,
    "write_bytes": 13287424,
    "wtime": 32
  },
  "prmon": {
    "Version": "3.1.1"
  }
}
